mdot_tnt/__init__.py
mdot_tnt/mdot.py
mdot_tnt/rounding.py
mdot_tnt/truncated_newton.py
mdot_tnt-0.1.0.dist-info/LICENSE
mdot_tnt-0.1.0.dist-info/METADATA
mdot_tnt-0.1.0.dist-info/WHEEL
mdot_tnt-0.1.0.dist-info/top_level.txt
mdot_tnt-0.1.0.dist-info/RECORD
