Metadata-Version: 2.1
Name: mdot-tnt
Version: 0.1.0
Summary: A fast, GPU-parallel, PyTorch-compatible optimal transport solver.
Author-email: Mete Kemertas <kemertas@cs.toronto.edu>
Project-URL: Homepage, https://github.com/metekemertas/mdot_tnt
Requires-Python: >=3.7
License-File: LICENSE
